{
  "code": 200,
  "status": "OK",
  "data": [
      {
        "accuseStack" : 0,
        "content" : "ㅁㄴㅇ",
        "emergencyFlag": false,
        "endTime": "2023-08-09 14:50",
        "friendFlag": false,
        "helpPostId": 1,
        "ipId": 3,
        "name": "강민석",
        "position": {"meetLatitude": "36.1071233", "meetLongitude": "128.416481", "meetAddr": "진평동"},
        "profileUrl": "http://k.kakaocdn.net/dn/bS2wdw/btreVxvFriB/kFFiMJpfHdDtEc6qnuqPQ0/img_110x110.jpg",
        "startTime": "2023-08-09 14:40"
      },
      {
        "accuseStack" : 0,
        "content" : "ㅁㄴㅇ",
        "emergencyFlag": true,
        "endTime": "2023-08-09 14:50",
        "friendFlag": false,
        "helpPostId": 3,
        "ipId": 3,
        "name": "강민석",
        "position": {"meetLatitude": "36.1071233", "meetLongitude": "128.216481", "meetAddr": "진평동"},
        "profileUrl": "http://k.kakaocdn.net/dn/bS2wdw/btreVxvFriB/kFFiMJpfHdDtEc6qnuqPQ0/img_110x110.jpg",
        "startTime": "2023-08-09 14:40"
      }
  ]
}